Metadata-Version: 2.1
Name: MojangSkin
Version: 1.0.0
Summary: Get Minecraft player skins
Home-page: https://github.com/legopitstop/mojangskin
Author: Legopitstop
Author-email: officiallegopitstop@gmail.com
License: MIT
Keywords: minecraft,skin,images,Pillow
Platform: UNKNOWN
Classifier: Development Status :: 5 - Production/Stable
Classifier: Intended Audience :: Developers
Classifier: Topic :: Software Development :: Build Tools
Classifier: License :: OSI Approved :: MIT License
Classifier: Operating System :: Microsoft :: Windows
Classifier: Programming Language :: Python :: 3.9
Requires-Python: >=3.6
License-File: LICENSE.md
